rspace_client/.spyproject/config/workspace.ini
rspace_client/__init__.py
rspace_client/client_base.py
rspace_client/eln/advanced_query_builder.py
rspace_client/eln/dcs.py
rspace_client/eln/eln.py
rspace_client/eln/field_content.py
rspace_client/eln/filetree_importer.py
rspace_client/eln/fs.py
rspace_client/fs_utils.py
rspace_client/inv/attachment_fs.py
rspace_client/inv/inv.py
rspace_client/inv/quantity_unit.py
rspace_client/inv/sample_builder2.py
rspace_client/inv/template_builder.py
rspace_client/utils.py
rspace_client/validators.py
rspace_client-2.6.1.dist-info/LICENSE
rspace_client-2.6.1.dist-info/METADATA
rspace_client-2.6.1.dist-info/WHEEL
rspace_client-2.6.1.dist-info/RECORD
