Metadata-Version: 2.3
Name: rspace-client
Version: 2.6.1
Summary: A client for calling RSpace ELN and Inventory APIs
License: Apache-2.0
Keywords: RSpace,ResearchSpace,ELN,Inventory
Author: Research Innovations Ltd
Author-email: support@researchspace.com
Maintainer: Matthias Kowalski
Maintainer-email: matthias@researchspace.com
Requires-Python: >=3.7.11,<4.0.0
Classifier: Development Status :: 4 - Beta
Classifier: Intended Audience :: Developers
Classifier: Intended Audience :: Science/Research
Classifier: License :: OSI Approved :: Apache Software License
Classifier: Programming Language :: Python :: 3
Classifier: Programming Language :: Python :: 3.8
Classifier: Programming Language :: Python :: 3.9
Classifier: Programming Language :: Python :: 3.10
Classifier: Programming Language :: Python :: 3.11
Classifier: Programming Language :: Python :: 3.12
Classifier: Programming Language :: Python :: 3.13
Classifier: Topic :: Software Development :: Libraries
Requires-Dist: beautifulsoup4 (>=4.9.3,<5.0.0)
Requires-Dist: fs (>=2.4.16,<3.0.0)
Requires-Dist: requests (>=2.25.1,<3.0.0)
Project-URL: Documentation, https://github.com/rspace-os/rspace-client-python
Project-URL: Repository, https://github.com/rspace-os/rspace-client-python
